[
  {
    "name": "Marketing",
    "personas": [
      {
        "name": "Derek Moss",
        "position": "CEO",
        "email_short": "derek",
        "phone": "123456789",
        "img": "https://goo.gl/gxVGxx"
      },
      {
        "name": "Melinda Davis",
        "position": "Co-CEO",
        "email_short": "melinda",
        "phone": "123456789",
        "img": "https://goo.gl/gxVGxx"
      },
      {
        "name": "Winston Lloyd",
        "position": "Marketing",
        "email_short": "winston",
        "phone": "123456789",
        "img": "https://goo.gl/gxVGxx"
      }
    ]
  },
  {
    "name": "IT",
    "personas": [
      {
        "name": "Kim Young",
        "position": "Back End Developer",
        "email_short": "kim",
        "phone": "123456789",
        "img": "https://goo.gl/gxVGxx"
      },
      {
        "name": "Dzianis Makeichyk",
        "position": "Front End Developer",
        "email_short": "dzianis",
        "phone": "123456789",
        "img": "https://goo.gl/gxVGxx"
      }
    ]
  }
]